{
  "/My-Blog/about-f66": {
    "__comp": "7792a21f",
    "__context": {
      "plugin": "a7456010"
    },
    "config": "5e9f5e1a"
  },
  "/My-Blog/blog-a1b": {
    "__comp": "a6aa9e1f",
    "__context": {
      "plugin": "36994c47"
    },
    "sidebar": "814f3328",
    "items": [
      {
        "content": "b1249810"
      },
      {
        "content": "1318337e"
      },
      {
        "content": "148b235c"
      },
      {
        "content": "a5b791e7"
      },
      {
        "content": "b02a2287"
      },
      {
        "content": "787477f2"
      },
      {
        "content": "bdb9db0f"
      }
    ],
    "__props": "f6c663d1"
  },
  "/My-Blog/blog/archive-329": {
    "__comp": "9e4087bc",
    "__context": {
      "plugin": "36994c47"
    },
    "__props": "c94cc383"
  },
  "/My-Blog/blog/authors-e07": {
    "__comp": "621db11d",
    "__context": {
      "data": {
        "blogMetadata": "acecf23e"
      },
      "plugin": "36994c47"
    },
    "sidebar": "814f3328",
    "__props": "6b54e36d"
  },
  "/My-Blog/blog/dealing-with-expectations-147": {
    "__comp": "ccc49370",
    "__context": {
      "data": {
        "blogMetadata": "acecf23e"
      },
      "plugin": "36994c47"
    },
    "sidebar": "814f3328",
    "content": "e742cdc5"
  },
  "/My-Blog/blog/first-blog-post-d37": {
    "__comp": "ccc49370",
    "__context": {
      "data": {
        "blogMetadata": "acecf23e"
      },
      "plugin": "36994c47"
    },
    "sidebar": "814f3328",
    "content": "054abd07"
  },
  "/My-Blog/blog/how-life-has-been-going-these-past-few-years-4f3": {
    "__comp": "ccc49370",
    "__context": {
      "data": {
        "blogMetadata": "acecf23e"
      },
      "plugin": "36994c47"
    },
    "sidebar": "814f3328",
    "content": "847385ef"
  },
  "/My-Blog/blog/My-Car-cc1": {
    "__comp": "ccc49370",
    "__context": {
      "data": {
        "blogMetadata": "acecf23e"
      },
      "plugin": "36994c47"
    },
    "sidebar": "814f3328",
    "content": "507e2fe7"
  },
  "/My-Blog/blog/my-time-in-taos-70a": {
    "__comp": "ccc49370",
    "__context": {
      "data": {
        "blogMetadata": "acecf23e"
      },
      "plugin": "36994c47"
    },
    "sidebar": "814f3328",
    "content": "5cccb6d9"
  },
  "/My-Blog/blog/plans-for-this-year-dc8": {
    "__comp": "ccc49370",
    "__context": {
      "data": {
        "blogMetadata": "acecf23e"
      },
      "plugin": "36994c47"
    },
    "sidebar": "814f3328",
    "content": "4f67eec2"
  },
  "/My-Blog/blog/tags-9e1": {
    "__comp": "01a85c17",
    "__context": {
      "plugin": "36994c47"
    },
    "sidebar": "814f3328",
    "__props": "d785a274"
  },
  "/My-Blog/blog/tags/car-781": {
    "__comp": "6875c492",
    "__context": {
      "plugin": "36994c47"
    },
    "sidebar": "814f3328",
    "items": [
      {
        "content": "787477f2"
      }
    ],
    "__props": "c1de2a13"
  },
  "/My-Blog/blog/tags/goals-887": {
    "__comp": "6875c492",
    "__context": {
      "plugin": "36994c47"
    },
    "sidebar": "814f3328",
    "items": [
      {
        "content": "b1249810"
      },
      {
        "content": "1318337e"
      },
      {
        "content": "148b235c"
      },
      {
        "content": "a5b791e7"
      }
    ],
    "__props": "81d3e5f2"
  },
  "/My-Blog/blog/tags/jobs-367": {
    "__comp": "6875c492",
    "__context": {
      "plugin": "36994c47"
    },
    "sidebar": "814f3328",
    "items": [
      {
        "content": "b02a2287"
      },
      {
        "content": "bdb9db0f"
      }
    ],
    "__props": "76f632f9"
  },
  "/My-Blog/blog/why-i-deleted-my-social-media-8a3": {
    "__comp": "ccc49370",
    "__context": {
      "data": {
        "blogMetadata": "acecf23e"
      },
      "plugin": "36994c47"
    },
    "sidebar": "814f3328",
    "content": "1afca45c"
  },
  "/My-Blog/markdown-page-f9b": {
    "__comp": "1f391b9e",
    "__context": {
      "plugin": "a7456010"
    },
    "content": "393be207"
  },
  "/My-Blog/docs-9d7": {
    "__comp": "5e95c892",
    "__context": {
      "plugin": "aba21aa0"
    }
  },
  "/My-Blog/docs-336": {
    "__comp": "a7bd4aaa",
    "__props": "249abd0b"
  },
  "/My-Blog/docs-911": {
    "__comp": "a94703ab"
  },
  "/My-Blog/docs/category/custom-title-3cb": {
    "__comp": "14eb3368",
    "__props": "5ffa94e0"
  },
  "/My-Blog/docs/getting started/alerts-b5f": {
    "__comp": "17896441",
    "content": "270c0592"
  },
  "/My-Blog/docs/getting started/codeblocks-2fe": {
    "__comp": "17896441",
    "content": "1333e0c7"
  },
  "/My-Blog/docs/getting started/markdown-ffc": {
    "__comp": "17896441",
    "content": "a4ec97d4"
  },
  "/My-Blog/docs/getting started/mdx-6cd": {
    "__comp": "17896441",
    "content": "95566ef7"
  },
  "/My-Blog/docs/getting started/table-of-contents-4a5": {
    "__comp": "17896441",
    "content": "aa530b7f"
  },
  "/My-Blog/docs/getting started/tabs-65f": {
    "__comp": "17896441",
    "content": "b7b5789b"
  },
  "/My-Blog/docs/single-page-ba7": {
    "__comp": "17896441",
    "content": "d76b4426"
  },
  "/My-Blog/-cd2": {
    "__comp": "c4f5d8e4",
    "__context": {
      "plugin": "a7456010"
    },
    "config": "5e9f5e1a"
  }
}